eval_jsonpath_elam/__init__.py
eval_jsonpath_elam/evalpath.py
eval_jsonpath_elam-0.0.1.dist-info/LICENSE.txt
eval_jsonpath_elam-0.0.1.dist-info/METADATA
eval_jsonpath_elam-0.0.1.dist-info/WHEEL
eval_jsonpath_elam-0.0.1.dist-info/top_level.txt
eval_jsonpath_elam-0.0.1.dist-info/RECORD
