Metadata-Version: 2.1
Name: eval-jsonpath-elam
Version: 0.0.1
Summary: Given a json value, this method will generate an eval jsonPath string for Python or dot notation string for Java/Javascript
Author-email: Eric Lam <ericlamqa@quadfactor.com>
Maintainer-email: Eric Lam <ericlamqa@quadfactor.com>
License: GNU AFFERO GENERAL PUBLIC LICENSE
Project-URL: GitHub, https://github.com/genericGenie
Project-URL: LinkedIn, https://www.linkedin.com/in/genericlam
Keywords: return,jsonpath,string,get,eval,eval(),generate,path,json,aggregate,collect,collected,collection,array,dict,dictionary,list,tree,dot,notation,branch,recursive,recursion,build,join,javascript,java,brackets,sequential,sequence,traverse,traversal,chain
Classifier: Programming Language :: Python :: 3.11
Classifier: License :: OSI Approved :: GNU Affero General Public License v3 or later (AGPLv3+)
Classifier: Operating System :: Microsoft :: Windows :: Windows 11
Requires-Python: >=3.11.4
License-File: LICENSE.txt
